segment_studio/__init__.py
segment_studio/segment_studio.py
segment_studio-0.0.3.dist-info/LICENSE
segment_studio-0.0.3.dist-info/METADATA
segment_studio-0.0.3.dist-info/WHEEL
segment_studio-0.0.3.dist-info/top_level.txt
segment_studio-0.0.3.dist-info/RECORD
