Metadata-Version: 2.1
Name: segment-studio
Version: 0.0.3
Summary: Segmentation Studio
Home-page: https://github.com/shanmukanaks/Segment-Studio.git
Author: shanmukanaks
Author-email: shanmukanaks@gmail.com
Keywords: object detection image editor segmention
Classifier: Programming Language :: Python :: 3.9
License-File: LICENSE
